rubetools/__init__.py
rubetools/__version__.py
rubetools/annotation.py
rubetools/detection.py
rubetools/eda.py
rubetools/metric_utils.py
rubetools/object.py
rubetools/utils.py
rubetools/formats/__init__.py
rubetools/formats/base.py
rubetools/formats/labelme.py
rubetools/formats/mscoco.py
rubetools/formats/pascalvoc.py
rubetools/formats/via.py
rubetools/formats/yolo.py
rubetools/formats/yolov4.py
rubetools/shapes/__init__.py
rubetools/shapes/hbox.py
rubetools/shapes/keypoints.py
rubetools/shapes/polygon.py
rubetools/shapes/shape.py
rubetools-1.0.3.dist-info/METADATA
rubetools-1.0.3.dist-info/WHEEL
rubetools-1.0.3.dist-info/top_level.txt
rubetools-1.0.3.dist-info/RECORD
